taylorist/__init__.py
taylorist/__main__.py
taylorist/py.typed
taylorist/ai/__init__.py
taylorist/ai/llm/__init__.py
taylorist/ai/llm/model_defination.py
taylorist/ai/llm/provider_defination.py
taylorist/ai/llm/taylorist_llm.py
taylorist/ai/stt/__init__.py
taylorist/ai/stt/model_defination.py
taylorist/ai/stt/provider_defination.py
taylorist/ai/stt/taylorist_stt.py
taylorist/ai/tts/__init__.py
taylorist/ai/tts/model_defination.py
taylorist/ai/tts/provider_defination.py
taylorist/ai/tts/taylorist_tts.py
taylorist/ai/tts/voice_defination.py
taylorist/ai/types/__init__.py
taylorist/ai/types/io_types.py
taylorist/converters/__init__.py
taylorist/converters/converter_input.py
taylorist/converters/converter_output.py
taylorist/errors/__init__.py
taylorist/errors/exception.py
taylorist/server/__init__.py
taylorist/server/endpoints.py
taylorist/server/server.py
taylorist-0.1.0.dist-info/licenses/LICENSE
taylorist-0.1.0.dist-info/METADATA
taylorist-0.1.0.dist-info/WHEEL
taylorist-0.1.0.dist-info/top_level.txt
taylorist-0.1.0.dist-info/RECORD
