Metadata-Version: 2.4
Name: taylorist
Version: 0.1.0
Home-page: https://github.com/umutkrts07/taylorist
Author: umutkrts
Project-URL: Bug Tracker, https://github.com/umutkrts07/taylorist/issues
Project-URL: Source Code, https://github.com/umutkrts07/taylorist
Classifier: Programming Language :: Python :: 3
Classifier: License :: OSI Approved :: MIT License
Classifier: Operating System :: OS Independent
Requires-Python: >=3.8
License-File: LICENSE
Requires-Dist: httpx>=0.28.1
Requires-Dist: requests>=2.32.3
Requires-Dist: pydantic>=2.11.5
Requires-Dist: aiohttp>=3.12.7
Dynamic: author
Dynamic: classifier
Dynamic: description
Dynamic: description-content-type
Dynamic: home-page
Dynamic: license-file
Dynamic: project-url
Dynamic: requires-dist
Dynamic: requires-python
